solvecaptcha/__init__.py
solvecaptcha/api.py
solvecaptcha/solver.py
solvecaptcha_python-1.0.2.dist-info/licenses/LICENSE
solvecaptcha_python-1.0.2.dist-info/METADATA
solvecaptcha_python-1.0.2.dist-info/WHEEL
solvecaptcha_python-1.0.2.dist-info/top_level.txt
solvecaptcha_python-1.0.2.dist-info/RECORD
