Metadata-Version: 2.4
Name: solvecaptcha-python
Version: 1.0.2
Summary: Python module for easy integration with solvecaptcha.com API
Home-page: https://github.com/solvercaptcha/solvecaptcha-python/
Author: solvecaptcha.com
Author-email: info@solvecaptcha.com
Keywords: solvecaptcha,captcha,api,captcha solver,reCAPTCHA,FunCaptcha,Geetest,image captcha,Coordinates,Click Captcha,Geetest V4,Lemin captcha,Amazon WAF,Cloudflare Turnstile,hcaptcha
Classifier: Programming Language :: Python :: 3
Classifier: License :: OSI Approved :: MIT License
Classifier: Operating System :: OS Independent
Classifier: Topic :: Software Development :: Libraries :: Python Modules
Classifier: Topic :: Scientific/Engineering :: Image Recognition
Classifier: Topic :: Utilities
Classifier: Intended Audience :: Developers
Requires-Python: >=3.6
License-File: LICENSE
Requires-Dist: requests
Dynamic: author
Dynamic: author-email
Dynamic: classifier
Dynamic: description
Dynamic: description-content-type
Dynamic: home-page
Dynamic: keywords
Dynamic: license-file
Dynamic: requires-dist
Dynamic: requires-python
Dynamic: summary
